LICENSE
README.md
setup.cfg
setup.py
alpaca_api/__init__.py
alpaca_api/historical_data.py
alpaca_api_py.egg-info/PKG-INFO
alpaca_api_py.egg-info/SOURCES.txt
alpaca_api_py.egg-info/dependency_links.txt
alpaca_api_py.egg-info/requires.txt
alpaca_api_py.egg-info/top_level.txt