Metadata-Version: 1.0
Name: alpaca-api-py
Version: 0.1.0
Summary: Alpaca API interface
Home-page: https://github.com/shuds13/pyexample
Author: Kekoa Yamaguchi
Author-email: example@email.com
License: BSD 2-clause
Platform: UNKNOWN
